calcrule_commission/__init__.py
calcrule_commission/admin.py
calcrule_commission/apps.py
calcrule_commission/calculation_rule.py
calcrule_commission/config.py
calcrule_commission/models.py
calcrule_commission/tests.py
calcrule_commission/urls.py
calcrule_commission/views.py
calcrule_commission/converters/__init__.py
calcrule_commission/converters/batch_run_to_bill.py
calcrule_commission/converters/premium_to_bill_item.py
calcrule_commission/migrations/__init__.py
openimis_be_calcrule_commission-1.6.1.dist-info/LICENSE.md
openimis_be_calcrule_commission-1.6.1.dist-info/METADATA
openimis_be_calcrule_commission-1.6.1.dist-info/WHEEL
openimis_be_calcrule_commission-1.6.1.dist-info/top_level.txt
openimis_be_calcrule_commission-1.6.1.dist-info/RECORD
