Metadata-Version: 2.1
Name: openimis-be-calcrule_commission
Version: 1.6.1
Summary: The openIMIS Backend calculation rule commision reference module.
Home-page: https://openimis.org/
Author: Seweryn Niedzielski
Author-email: sniedzielski@soldevelo.com
License: GNU AGPL v3
Classifier: Environment :: Web Environment
Classifier: Framework :: Django
Classifier: Framework :: Django :: 2.1
Classifier: Intended Audience :: Developers
Classifier: License :: OSI Approved :: GNU Affero General Public License v3
Classifier: Operating System :: OS Independent
Classifier: Programming Language :: Python
Classifier: Programming Language :: Python :: 3.6
Classifier: Programming Language :: Python :: 3.7
License-File: LICENSE.md
Requires-Dist: django
Requires-Dist: django-db-signals
Requires-Dist: djangorestframework
Requires-Dist: openimis-be-core
Requires-Dist: openimis-be-calculation
